{
    "server_ip": "10.0.7.10",
    "udp_port": 5005,
    "tcp_port": 5006,
    "agents": [
        {
            "agent_id": 1,
            "tasks": [
                {
                    "task_id": "task-001",
                    "metric_type": "latency",
                    "frequency": 10,
                    "threshold": 44,
                    "tcp_port": 5006
                },
                {
                    "task_id": "task-002",
                    "metric_type": "cpu_usage",
                    "frequency": 20,
                    "threshold": 42,
                    "tcp_port": 5006
                }
            ]
        },
        {
            "agent_id": 2,
            "tasks": [
                {
                    "task_id": "task-003",
                    "metric_type": "bandwidth",
                    "frequency": 15,
                    "threshold": 12,
                    "tcp_port": 5006
                }
            ]
        }
    ]
}
